{
  "task": "xml_file_upload", 
  "depends_on": [
    "completed@xml_upload_to_aws", 
    "completed@prepare_metadata_xml"
  ], 
  "tool": "upload", 
  "command": "upload.py", 
  "input": {
    "file_name": "bundle.EGAR00001115896.xml", 
    "object_id": "ed8732b0-0a93-5b29-8888-cf57f956c92c", 
    "file_md5sum": "235e2cb0039ae5b4323305b5a5fadfab", 
    "file": "/home/ubuntu/jtracker/worker.1499715228.c40c55ff.host.76674056.10.10.0.19/job.EGAR00001115896.LINC-JP.HCC90T.EGAN00001086037/task.prepare_metadata_xml/bundle.EGAR00001115896.xml", 
    "file_size": 3663, 
    "bundle_id": "EGAR00001115896"
  }, 
  "runtime": {
    "docker": null
  }
}