{
  "task": "xml_file_upload", 
  "depends_on": [
    "completed@xml_upload_to_aws", 
    "completed@prepare_metadata_xml"
  ], 
  "tool": "upload", 
  "command": "upload.py", 
  "output": [
    {
      "_jt_": {
        "worker_id": "worker.1501684120.9acac567.host.76674056.10.10.0.19", 
        "workflow_version": "0.6.7", 
        "jt_version": "0.1.0rc9", 
        "task_state": "completed"
      }, 
      "runtime": {
        "task_start": 1501738776, 
        "task_stop": 1501738791
      }
    }
  ], 
  "input": {
    "file_name": "bundle.EGAR00001262812.xml", 
    "object_id": "129e5272-b48a-5a3b-a120-b2a233fd4fb2", 
    "file_md5sum": "2bda3695108fe67d0856fb87a734513b", 
    "file": "/home/ubuntu/jtracker/worker.1501684120.9acac567.host.76674056.10.10.0.19/job.EGAR00001262812.BTCA-JP.BD201T.EGAN00001247044/task.prepare_metadata_xml/bundle.EGAR00001262812.xml", 
    "file_size": 3186, 
    "bundle_id": "EGAR00001262812"
  }, 
  "runtime": {
    "docker": null
  }
}