{
  "task": "xml_file_upload", 
  "depends_on": [
    "completed@xml_upload_to_aws", 
    "completed@prepare_metadata_xml"
  ], 
  "tool": "upload", 
  "command": "upload.py", 
  "output": [
    {
      "_jt_": {
        "worker_id": "worker.1499805416.a2426c62.host.231181a3.10.10.1.7", 
        "workflow_version": "0.6.7", 
        "jt_version": "0.1.0rc9", 
        "task_state": "completed"
      }, 
      "runtime": {
        "task_start": 1501014769, 
        "task_stop": 1501014786
      }
    }
  ], 
  "input": {
    "file_name": "bundle.EGAR00001255878.xml", 
    "object_id": "eae12043-fe32-5b2a-aa19-284cf8b7d46d", 
    "file_md5sum": "5afc48fae52a8f4d92d376c2b8603673", 
    "file": "/home/ubuntu/jtracker/worker.1499805416.a2426c62.host.231181a3.10.10.1.7/job.EGAR00001255878.BTCA-JP.BD20T.EGAN00001246824/task.prepare_metadata_xml/bundle.EGAR00001255878.xml", 
    "file_size": 3174, 
    "bundle_id": "EGAR00001255878"
  }, 
  "runtime": {
    "docker": null
  }
}