{
  "task": "xml_upload_to_aws", 
  "depends_on": [
    "completed@prepare_metadata_xml"
  ], 
  "tool": "upload_to_aws", 
  "command": "upload_to_aws.py", 
  "input": {
    "file_name": "bundle.EGAR00001114448.xml", 
    "object_id": "2e3616e6-908f-597a-97aa-de3343a92f35", 
    "file_md5sum": "020d7a5d99964b3093cd3624134e5213", 
    "file": "/home/ubuntu/jtracker/worker.1499460317.ae7ebd11.host.032f1807.10.10.0.3/job.EGAR00001114448.LINC-JP.HCC71T.EGAN00001086021/task.prepare_metadata_xml/bundle.EGAR00001114448.xml", 
    "file_size": 3665, 
    "bundle_id": "EGAR00001114448", 
    "project_code": "LINC-JP"
  }, 
  "runtime": {
    "docker": null
  }
}