{
  "task": "xml_file_upload", 
  "depends_on": [
    "completed@xml_upload_to_aws", 
    "completed@prepare_metadata_xml"
  ], 
  "tool": "upload", 
  "command": "upload.py", 
  "input": {
    "file_name": "bundle.EGAR00001117162.xml", 
    "object_id": "5cf8be2b-f6c6-5d81-b2f2-14de2819cc35", 
    "file_md5sum": "21b766721c9a4a0600bec772d32706f7", 
    "file": "/home/ubuntu/jtracker/worker.1499784243.85d5d05e.host.032f1807.10.10.0.3/job.EGAR00001117162.LINC-JP.HCC102T.EGAN00001086046/task.prepare_metadata_xml/bundle.EGAR00001117162.xml", 
    "file_size": 3667, 
    "bundle_id": "EGAR00001117162"
  }, 
  "runtime": {
    "docker": null
  }
}