{
  "task": "xml_upload_to_aws", 
  "depends_on": [
    "completed@prepare_metadata_xml"
  ], 
  "tool": "upload_to_aws", 
  "command": "upload_to_aws.py", 
  "input": {
    "file_name": "bundle.EGAR00001194563.xml", 
    "object_id": "127cd9c6-7fd7-577a-b327-56d4d49df192", 
    "file_md5sum": "86f6698dca6f64a25337394e87da537e", 
    "file": "/home/ubuntu/jtracker/worker.1499784243.85d5d05e.host.032f1807.10.10.0.3/job.EGAR00001194563.LINC-JP.CCC4T.EGAN00001196926/task.prepare_metadata_xml/bundle.EGAR00001194563.xml", 
    "file_size": 3499, 
    "bundle_id": "EGAR00001194563", 
    "project_code": "LINC-JP"
  }, 
  "runtime": {
    "docker": null
  }
}