{
  "task": "xml_file_upload", 
  "depends_on": [
    "completed@xml_upload_to_aws", 
    "completed@prepare_metadata_xml"
  ], 
  "tool": "upload", 
  "command": "upload.py", 
  "input": {
    "file_name": "bundle.EGAR00001269857.xml", 
    "object_id": "18dc5cbe-5805-5799-816e-b7b111b81b0e", 
    "file_md5sum": "d4269eaa5bf93ac8e977bf4c3355d191", 
    "file": "/home/ubuntu/jtracker/worker.1504120675.a58629fc.host.4b92f40d.10.10.0.24/job.EGAR00001269857.SKCA-BR.ML_68_T_01.EGAN00001252331/task.prepare_metadata_xml/bundle.EGAR00001269857.xml", 
    "file_size": 3523, 
    "bundle_id": "EGAR00001269857"
  }, 
  "runtime": {
    "docker": null
  }
}