{
  "task": "xml_file_upload", 
  "depends_on": [
    "completed@xml_upload_to_aws", 
    "completed@prepare_metadata_xml"
  ], 
  "tool": "upload", 
  "command": "upload.py", 
  "output": [
    {
      "_jt_": {
        "worker_id": "worker.1499805416.a2426c62.host.231181a3.10.10.1.7", 
        "workflow_version": "0.6.7", 
        "jt_version": "0.1.0rc9", 
        "task_state": "completed"
      }, 
      "runtime": {
        "task_start": 1500942194, 
        "task_stop": 1500942210
      }
    }
  ], 
  "input": {
    "file_name": "bundle.EGAR00001255039.xml", 
    "object_id": "92569d00-7cd9-5e7d-a78f-8fbf1906b5bd", 
    "file_md5sum": "d725b32214ea2728437a522ac86be6b8", 
    "file": "/home/ubuntu/jtracker/worker.1499805416.a2426c62.host.231181a3.10.10.1.7/job.EGAR00001255039.BTCA-JP.BD5T.EGAN00001246810/task.prepare_metadata_xml/bundle.EGAR00001255039.xml", 
    "file_size": 3166, 
    "bundle_id": "EGAR00001255039"
  }, 
  "runtime": {
    "docker": null
  }
}