{
  "task": "xml_upload_to_aws", 
  "depends_on": [
    "completed@prepare_metadata_xml"
  ], 
  "tool": "upload_to_aws", 
  "command": "upload_to_aws.py", 
  "input": {
    "file_name": "bundle.EGAR00001119500.xml", 
    "object_id": "0046364b-4ca1-5040-82a3-a5ef30e894f8", 
    "file_md5sum": "993e65283b9c3480727f2e944a7fca6b", 
    "file": "/home/ubuntu/jtracker/worker.1499460317.ae7ebd11.host.032f1807.10.10.0.3/job.EGAR00001119500.LINC-JP.HCC132T.EGAN00001086068/task.prepare_metadata_xml/bundle.EGAR00001119500.xml", 
    "file_size": 3665, 
    "bundle_id": "EGAR00001119500", 
    "project_code": "LINC-JP"
  }, 
  "runtime": {
    "docker": null
  }
}