{
  "task": "xml_upload_to_aws", 
  "depends_on": [
    "completed@prepare_metadata_xml"
  ], 
  "tool": "upload_to_aws", 
  "command": "upload_to_aws.py", 
  "input": {
    "file_name": "bundle.EGAR00001115767.xml", 
    "object_id": "134308c0-dc5f-5935-b3e2-e5dcec35d659", 
    "file_md5sum": "e6a4b88c6db85decba63a1b95c57c93b", 
    "file": "/home/ubuntu/jtracker/worker.1499715228.c40c55ff.host.76674056.10.10.0.19/job.EGAR00001115767.LINC-JP.HCC89T.EGAN00001086036/task.prepare_metadata_xml/bundle.EGAR00001115767.xml", 
    "file_size": 3663, 
    "bundle_id": "EGAR00001115767", 
    "project_code": "LINC-JP"
  }, 
  "runtime": {
    "docker": null
  }
}