{
  "task": "xml_upload_to_aws", 
  "depends_on": [
    "completed@prepare_metadata_xml"
  ], 
  "tool": "upload_to_aws", 
  "command": "upload_to_aws.py", 
  "output": [
    {
      "idx_file_size": 0, 
      "idx_file_md5sum": null, 
      "_jt_": {
        "worker_id": "worker.1499715228.c40c55ff.host.76674056.10.10.0.19", 
        "workflow_version": "0.6.7", 
        "jt_version": "0.1.0rc9", 
        "task_state": "completed"
      }, 
      "idx_file": null, 
      "allowed_upload": false, 
      "file_md5sum": "26edefed948c0e3568046d9c7a7096e4", 
      "file": "/home/ubuntu/jtracker/worker.1499715228.c40c55ff.host.76674056.10.10.0.19/job.EGAR00001262637.BTCA-JP.BD200T.EGAN00001247043/task.prepare_metadata_xml/bundle.EGAR00001262637.xml", 
      "file_size": 0, 
      "runtime": {
        "task_start": 1501363784, 
        "task_stop": 1501363784
      }
    }
  ], 
  "input": {
    "file_name": "bundle.EGAR00001262637.xml", 
    "object_id": "2e4e4f5a-38f1-58d6-a42a-5a0ccb40928b", 
    "file_md5sum": "26edefed948c0e3568046d9c7a7096e4", 
    "file": "/home/ubuntu/jtracker/worker.1499715228.c40c55ff.host.76674056.10.10.0.19/job.EGAR00001262637.BTCA-JP.BD200T.EGAN00001247043/task.prepare_metadata_xml/bundle.EGAR00001262637.xml", 
    "file_size": 3186, 
    "bundle_id": "EGAR00001262637", 
    "project_code": "BTCA-JP"
  }, 
  "runtime": {
    "docker": null
  }
}