{
  "task": "xml_file_upload", 
  "depends_on": [
    "completed@xml_upload_to_aws", 
    "completed@prepare_metadata_xml"
  ], 
  "tool": "upload", 
  "command": "upload.py", 
  "input": {
    "file_name": "bundle.EGAR00001119635.xml", 
    "object_id": "2958419e-cae8-5c98-81e1-32c390e89a06", 
    "file_md5sum": "b5f429b6561cf09033f37656053e616d", 
    "file": "/home/ubuntu/jtracker/worker.1499176194.c9c0a759.host.231181a3.10.10.1.7/job.EGAR00001119635.LINC-JP.HCC134T.EGAN00001086070/task.prepare_metadata_xml/bundle.EGAR00001119635.xml", 
    "file_size": 3669, 
    "bundle_id": "EGAR00001119635"
  }, 
  "runtime": {
    "docker": null
  }
}