{
  "task": "xml_file_upload", 
  "depends_on": [
    "completed@xml_upload_to_aws", 
    "completed@prepare_metadata_xml"
  ], 
  "tool": "upload", 
  "command": "upload.py", 
  "output": [
    {
      "_jt_": {
        "worker_id": "worker.1499715228.c40c55ff.host.76674056.10.10.0.19", 
        "workflow_version": "0.6.7", 
        "jt_version": "0.1.0rc9", 
        "task_state": "completed"
      }, 
      "runtime": {
        "task_start": 1501281411, 
        "task_stop": 1501281429
      }
    }
  ], 
  "input": {
    "file_name": "bundle.EGAR00001262468.xml", 
    "object_id": "ef52ffaa-1dec-59da-b661-aa53187f6401", 
    "file_md5sum": "ba789564426b77827fe3508e71d799de", 
    "file": "/home/ubuntu/jtracker/worker.1499715228.c40c55ff.host.76674056.10.10.0.19/job.EGAR00001262468.BTCA-JP.BD197T.EGAN00001247041/task.prepare_metadata_xml/bundle.EGAR00001262468.xml", 
    "file_size": 3186, 
    "bundle_id": "EGAR00001262468"
  }, 
  "runtime": {
    "docker": null
  }
}