{
  "task": "xml_upload_to_aws", 
  "depends_on": [
    "completed@prepare_metadata_xml"
  ], 
  "tool": "upload_to_aws", 
  "command": "upload_to_aws.py", 
  "input": {
    "file_name": "bundle.EGAR00001262161.xml", 
    "object_id": "df6b2704-6ae3-50db-a015-81dfd584ea01", 
    "file_md5sum": "3496003a2256fc3a537d4910020b2c4c", 
    "file": "/home/ubuntu/jtracker/worker.1501684194.e5542c01.host.2b33d591.10.10.0.20/job.EGAR00001262161.BTCA-JP.BD187T.EGAN00001246987/task.prepare_metadata_xml/bundle.EGAR00001262161.xml", 
    "file_size": 3186, 
    "bundle_id": "EGAR00001262161", 
    "project_code": "BTCA-JP"
  }, 
  "runtime": {
    "docker": null
  }
}