{
  "task": "xml_file_upload", 
  "depends_on": [
    "completed@xml_upload_to_aws", 
    "completed@prepare_metadata_xml"
  ], 
  "tool": "upload", 
  "command": "upload.py", 
  "output": [
    {
      "_jt_": {
        "worker_id": "worker.1499805416.a2426c62.host.231181a3.10.10.1.7", 
        "workflow_version": "0.6.7", 
        "jt_version": "0.1.0rc9", 
        "task_state": "completed"
      }, 
      "runtime": {
        "task_start": 1500887266, 
        "task_stop": 1500887282
      }
    }
  ], 
  "input": {
    "file_name": "bundle.EGAR00001255220.xml", 
    "object_id": "9408dfd7-8c7c-55c4-ac80-d1d3f0ac94fa", 
    "file_md5sum": "7d4ff096d0bc874c792cee947a8fce2d", 
    "file": "/home/ubuntu/jtracker/worker.1499805416.a2426c62.host.231181a3.10.10.1.7/job.EGAR00001255220.BTCA-JP.BD8T.EGAN00001246813/task.prepare_metadata_xml/bundle.EGAR00001255220.xml", 
    "file_size": 3164, 
    "bundle_id": "EGAR00001255220"
  }, 
  "runtime": {
    "docker": null
  }
}