{
  "task": "xml_upload_to_aws", 
  "depends_on": [
    "completed@prepare_metadata_xml"
  ], 
  "tool": "upload_to_aws", 
  "command": "upload_to_aws.py", 
  "output": [
    {
      "idx_file_size": 0, 
      "idx_file_md5sum": null, 
      "_jt_": {
        "worker_id": "worker.1499715228.c40c55ff.host.76674056.10.10.0.19", 
        "workflow_version": "0.6.7", 
        "jt_version": "0.1.0rc9", 
        "task_state": "completed"
      }, 
      "idx_file": null, 
      "allowed_upload": true, 
      "file_md5sum": "b8a1761e6076ad18f0366bd035f8f98a", 
      "file": "/home/ubuntu/jtracker/worker.1499715228.c40c55ff.host.76674056.10.10.0.19/job.EGAR00001115573.LINC-JP.HCC87T.EGAN00001086034/task.prepare_metadata_xml/bundle.EGAR00001115573.xml", 
      "file_size": 3663, 
      "runtime": {
        "task_start": 1500296552, 
        "task_stop": 1500296557
      }
    }
  ], 
  "input": {
    "file_name": "bundle.EGAR00001115573.xml", 
    "object_id": "fbbce021-f0fc-5f26-bb8f-359d077a3ed1", 
    "file_md5sum": "b8a1761e6076ad18f0366bd035f8f98a", 
    "file": "/home/ubuntu/jtracker/worker.1499715228.c40c55ff.host.76674056.10.10.0.19/job.EGAR00001115573.LINC-JP.HCC87T.EGAN00001086034/task.prepare_metadata_xml/bundle.EGAR00001115573.xml", 
    "file_size": 3663, 
    "bundle_id": "EGAR00001115573", 
    "project_code": "LINC-JP"
  }, 
  "runtime": {
    "docker": null
  }
}