{
  "task": "xml_file_upload", 
  "depends_on": [
    "completed@xml_upload_to_aws", 
    "completed@prepare_metadata_xml"
  ], 
  "tool": "upload", 
  "command": "upload.py", 
  "input": {
    "file_name": "bundle.EGAR00001262552.xml", 
    "object_id": "8533f3a4-8994-5568-ae23-0573c0197b0c", 
    "file_md5sum": "e796435e6ed27c38469b10910eb27b90", 
    "file": "/home/ubuntu/jtracker/worker.1501684194.e5542c01.host.2b33d591.10.10.0.20/job.EGAR00001262552.BTCA-JP.BD199T.EGAN00001247042/task.prepare_metadata_xml/bundle.EGAR00001262552.xml", 
    "file_size": 3186, 
    "bundle_id": "EGAR00001262552"
  }, 
  "runtime": {
    "docker": null
  }
}