{
  "task": "xml_upload_to_aws", 
  "depends_on": [
    "completed@prepare_metadata_xml"
  ], 
  "tool": "upload_to_aws", 
  "command": "upload_to_aws.py", 
  "input": {
    "file_name": "bundle.EGAR00001114519.xml", 
    "object_id": "0a8c0f9b-34f2-561f-93c9-5a0ad9f784f1", 
    "file_md5sum": "2be3ad00b0496e75bf36d9882c8eef85", 
    "file": "/home/ubuntu/jtracker/worker.1499457168.ac01eac3.host.231181a3.10.10.1.7/job.EGAR00001114519.LINC-JP.HCC73T.EGAN00001086023/task.prepare_metadata_xml/bundle.EGAR00001114519.xml", 
    "file_size": 3661, 
    "bundle_id": "EGAR00001114519", 
    "project_code": "LINC-JP"
  }, 
  "runtime": {
    "docker": null
  }
}