{
  "task": "xml_file_upload", 
  "depends_on": [
    "completed@xml_upload_to_aws", 
    "completed@prepare_metadata_xml"
  ], 
  "tool": "upload", 
  "command": "upload.py", 
  "output": [
    {
      "_jt_": {
        "worker_id": "worker.1499715228.c40c55ff.host.76674056.10.10.0.19", 
        "workflow_version": "0.6.7", 
        "jt_version": "0.1.0rc9", 
        "task_state": "completed"
      }, 
      "runtime": {
        "task_start": 1501488540, 
        "task_stop": 1501488556
      }
    }
  ], 
  "input": {
    "file_name": "bundle.EGAR00001262136.xml", 
    "object_id": "44fb2a21-e865-552a-bc1f-67358c1783c1", 
    "file_md5sum": "7da42e0df210aae0b1ca8c411e09dfbd", 
    "file": "/home/ubuntu/jtracker/worker.1499715228.c40c55ff.host.76674056.10.10.0.19/job.EGAR00001262136.BTCA-JP.BD186T.EGAN00001246986/task.prepare_metadata_xml/bundle.EGAR00001262136.xml", 
    "file_size": 3186, 
    "bundle_id": "EGAR00001262136"
  }, 
  "runtime": {
    "docker": null
  }
}