{
  "task": "xml_upload_to_aws", 
  "depends_on": [
    "completed@prepare_metadata_xml"
  ], 
  "tool": "upload_to_aws", 
  "command": "upload_to_aws.py", 
  "input": {
    "file_name": "bundle.EGAR00001119401.xml", 
    "object_id": "4905483e-dfa6-5b72-88b4-d6bceafd5e6f", 
    "file_md5sum": "{{xml_file_md5sum@prepare_metadata_xml}}", 
    "file": "{{xml_file@prepare_metadata_xml}}", 
    "file_size": "{{xml_file_size@prepare_metadata_xml}}", 
    "bundle_id": "EGAR00001119401", 
    "project_code": "LINC-JP"
  }, 
  "runtime": {
    "docker": null
  }
}