{
  "task": "xml_upload_to_aws", 
  "depends_on": [
    "completed@prepare_metadata_xml"
  ], 
  "tool": "upload_to_aws", 
  "command": "upload_to_aws.py", 
  "input": {
    "file_name": "bundle.EGAR00001119978.xml", 
    "object_id": "92322977-9b91-5a0a-9fce-776db1f63d52", 
    "file_md5sum": "52ca6d414179e95e50e51e487799de6b", 
    "file": "/home/ubuntu/jtracker/worker.1499715228.c40c55ff.host.76674056.10.10.0.19/job.EGAR00001119978.LINC-JP.HCC139T.EGAN00001086074/task.prepare_metadata_xml/bundle.EGAR00001119978.xml", 
    "file_size": 3667, 
    "bundle_id": "EGAR00001119978", 
    "project_code": "LINC-JP"
  }, 
  "runtime": {
    "docker": null
  }
}