{
  "task": "xml_file_upload", 
  "depends_on": [
    "completed@xml_upload_to_aws", 
    "completed@prepare_metadata_xml"
  ], 
  "tool": "upload", 
  "command": "upload.py", 
  "output": [
    {
      "_jt_": {
        "worker_id": "worker.1499784243.85d5d05e.host.032f1807.10.10.0.3", 
        "workflow_version": "0.6.7", 
        "jt_version": "0.1.0rc9", 
        "task_state": "completed"
      }, 
      "runtime": {
        "task_start": 1499837276, 
        "task_stop": 1499837290
      }
    }
  ], 
  "input": {
    "file_name": "bundle.EGAR00001119074.xml", 
    "object_id": "e37f4041-9dc3-509a-b5b2-380fa27d9b76", 
    "file_md5sum": "641b599b38c31dc3edc99e2dd7fef36d", 
    "file": "/home/ubuntu/jtracker/worker.1499784243.85d5d05e.host.032f1807.10.10.0.3/job.EGAR00001119074.LINC-JP.HCC123T.EGAN00001086062/task.prepare_metadata_xml/bundle.EGAR00001119074.xml", 
    "file_size": 3665, 
    "bundle_id": "EGAR00001119074"
  }, 
  "runtime": {
    "docker": null
  }
}