{
  "task": "xml_file_upload", 
  "depends_on": [
    "completed@xml_upload_to_aws", 
    "completed@prepare_metadata_xml"
  ], 
  "tool": "upload", 
  "command": "upload.py", 
  "output": [
    {
      "_jt_": {
        "worker_id": "worker.1499715228.c40c55ff.host.76674056.10.10.0.19", 
        "workflow_version": "0.6.7", 
        "jt_version": "0.1.0rc9", 
        "task_state": "completed"
      }, 
      "runtime": {
        "task_start": 1501439526, 
        "task_stop": 1501439542
      }
    }
  ], 
  "input": {
    "file_name": "bundle.EGAR00001262707.xml", 
    "object_id": "6d7c57b6-424b-5435-a5c6-31072f0a2374", 
    "file_md5sum": "9efa33e3f5741c346cec798bc48be3fb", 
    "file": "/home/ubuntu/jtracker/worker.1499715228.c40c55ff.host.76674056.10.10.0.19/job.EGAR00001262707.BTCA-JP.BD201T.EGAN00001247044/task.prepare_metadata_xml/bundle.EGAR00001262707.xml", 
    "file_size": 3186, 
    "bundle_id": "EGAR00001262707"
  }, 
  "runtime": {
    "docker": null
  }
}