{
  "task": "xml_upload_to_aws", 
  "depends_on": [
    "completed@prepare_metadata_xml"
  ], 
  "tool": "upload_to_aws", 
  "command": "upload_to_aws.py", 
  "input": {
    "file_name": "bundle.EGAR00001262520.xml", 
    "object_id": "aa0d2025-c1fa-5f68-8892-7a92418d5aef", 
    "file_md5sum": "{{xml_file_md5sum@prepare_metadata_xml}}", 
    "file": "{{xml_file@prepare_metadata_xml}}", 
    "file_size": "{{xml_file_size@prepare_metadata_xml}}", 
    "bundle_id": "EGAR00001262520", 
    "project_code": "BTCA-JP"
  }, 
  "runtime": {
    "docker": null
  }
}