{
  "task": "xml_file_upload", 
  "depends_on": [
    "completed@xml_upload_to_aws", 
    "completed@prepare_metadata_xml"
  ], 
  "tool": "upload", 
  "command": "upload.py", 
  "output": [
    {
      "_jt_": {
        "worker_id": "worker.1499715228.c40c55ff.host.76674056.10.10.0.19", 
        "workflow_version": "0.6.7", 
        "jt_version": "0.1.0rc9", 
        "task_state": "completed"
      }, 
      "runtime": {
        "task_start": 1500069461, 
        "task_stop": 1500069476
      }
    }
  ], 
  "input": {
    "file_name": "bundle.EGAR00001199190.xml", 
    "object_id": "d67aebf8-6134-5c6c-8bde-a794f69bd9ce", 
    "file_md5sum": "30de8cf5e5e90f7e7f2df8ca0abdfff7", 
    "file": "/home/ubuntu/jtracker/worker.1499715228.c40c55ff.host.76674056.10.10.0.19/job.EGAR00001199190.LINC-JP.HCC27T.EGAN00001196874/task.prepare_metadata_xml/bundle.EGAR00001199190.xml", 
    "file_size": 3505, 
    "bundle_id": "EGAR00001199190"
  }, 
  "runtime": {
    "docker": null
  }
}