{
  "task": "xml_file_upload", 
  "depends_on": [
    "completed@xml_upload_to_aws", 
    "completed@prepare_metadata_xml"
  ], 
  "tool": "upload", 
  "command": "upload.py", 
  "output": [
    {
      "_jt_": {
        "worker_id": "worker.1499805416.a2426c62.host.231181a3.10.10.1.7", 
        "workflow_version": "0.6.7", 
        "jt_version": "0.1.0rc9", 
        "task_state": "completed"
      }, 
      "runtime": {
        "task_start": 1500126003, 
        "task_stop": 1500126018
      }
    }
  ], 
  "input": {
    "file_name": "bundle.EGAR00001199151.xml", 
    "object_id": "c1c95a48-741c-5805-8072-6dab4b7896ce", 
    "file_md5sum": "bc00cd21d78df385fb23a127e9de1f20", 
    "file": "/home/ubuntu/jtracker/worker.1499805416.a2426c62.host.231181a3.10.10.1.7/job.EGAR00001199151.LINC-JP.HCC27T.EGAN00001196874/task.prepare_metadata_xml/bundle.EGAR00001199151.xml", 
    "file_size": 3505, 
    "bundle_id": "EGAR00001199151"
  }, 
  "runtime": {
    "docker": null
  }
}