{
  "task": "xml_upload_to_aws", 
  "depends_on": [
    "completed@prepare_metadata_xml"
  ], 
  "tool": "upload_to_aws", 
  "command": "upload_to_aws.py", 
  "input": {
    "file_name": "bundle.EGAR00001114883.xml", 
    "object_id": "468a8c93-7ad4-546d-8f45-46ee3bfa7992", 
    "file_md5sum": "f8b4ed12ceae5dca8790d2958aeeb80d", 
    "file": "/home/ubuntu/jtracker/worker.1499715228.c40c55ff.host.76674056.10.10.0.19/job.EGAR00001114883.LINC-JP.HCC78T.EGAN00001086028/task.prepare_metadata_xml/bundle.EGAR00001114883.xml", 
    "file_size": 3663, 
    "bundle_id": "EGAR00001114883", 
    "project_code": "LINC-JP"
  }, 
  "runtime": {
    "docker": null
  }
}