{
  "task": "xml_upload_to_aws", 
  "depends_on": [
    "completed@prepare_metadata_xml"
  ], 
  "tool": "upload_to_aws", 
  "command": "upload_to_aws.py", 
  "input": {
    "file_name": "bundle.EGAR00001114853.xml", 
    "object_id": "fa4be499-2958-56a5-b4c9-b2268cb68eca", 
    "file_md5sum": "d216e9eaa06400b1600e272456694bc8", 
    "file": "/home/ubuntu/jtracker/worker.1499784243.85d5d05e.host.032f1807.10.10.0.3/job.EGAR00001114853.LINC-JP.HCC78T.EGAN00001086028/task.prepare_metadata_xml/bundle.EGAR00001114853.xml", 
    "file_size": 3663, 
    "bundle_id": "EGAR00001114853", 
    "project_code": "LINC-JP"
  }, 
  "runtime": {
    "docker": null
  }
}