{
  "task": "xml_upload_to_aws", 
  "depends_on": [
    "completed@prepare_metadata_xml"
  ], 
  "tool": "upload_to_aws", 
  "command": "upload_to_aws.py", 
  "output": [
    {
      "idx_file_size": 0, 
      "idx_file_md5sum": null, 
      "_jt_": {
        "worker_id": "worker.1499784243.85d5d05e.host.032f1807.10.10.0.3", 
        "workflow_version": "0.6.7", 
        "jt_version": "0.1.0rc9", 
        "task_state": "completed"
      }, 
      "idx_file": null, 
      "allowed_upload": true, 
      "file_md5sum": "cb7f4cf01983ec41a89c28f4449261aa", 
      "file": "/home/ubuntu/jtracker/worker.1499784243.85d5d05e.host.032f1807.10.10.0.3/job.EGAR00001115112.LINC-JP.HCC82T.EGAN00001086030/task.prepare_metadata_xml/bundle.EGAR00001115112.xml", 
      "file_size": 3663, 
      "runtime": {
        "task_start": 1500235977, 
        "task_stop": 1500235982
      }
    }
  ], 
  "input": {
    "file_name": "bundle.EGAR00001115112.xml", 
    "object_id": "ae9eeef3-fbd9-528f-9980-b2d496102e67", 
    "file_md5sum": "cb7f4cf01983ec41a89c28f4449261aa", 
    "file": "/home/ubuntu/jtracker/worker.1499784243.85d5d05e.host.032f1807.10.10.0.3/job.EGAR00001115112.LINC-JP.HCC82T.EGAN00001086030/task.prepare_metadata_xml/bundle.EGAR00001115112.xml", 
    "file_size": 3663, 
    "bundle_id": "EGAR00001115112", 
    "project_code": "LINC-JP"
  }, 
  "runtime": {
    "docker": null
  }
}