{
  "task": "xml_file_upload", 
  "depends_on": [
    "completed@xml_upload_to_aws", 
    "completed@prepare_metadata_xml"
  ], 
  "tool": "upload", 
  "command": "upload.py", 
  "output": [
    {
      "_jt_": {
        "worker_id": "worker.1501684194.e5542c01.host.2b33d591.10.10.0.20", 
        "workflow_version": "0.6.7", 
        "jt_version": "0.1.0rc9", 
        "task_state": "completed"
      }, 
      "runtime": {
        "task_start": 1501838669, 
        "task_stop": 1501838685
      }
    }
  ], 
  "input": {
    "file_name": "bundle.EGAR00001263801.xml", 
    "object_id": "39b00c4e-f56e-5bc4-ab33-db3b94e813a3", 
    "file_md5sum": "ff68fed8a8c6e80e0d7fca94a06dba78", 
    "file": "/home/ubuntu/jtracker/worker.1501684194.e5542c01.host.2b33d591.10.10.0.20/job.EGAR00001263801.BTCA-JP.BD221T.EGAN00001247014/task.prepare_metadata_xml/bundle.EGAR00001263801.xml", 
    "file_size": 3184, 
    "bundle_id": "EGAR00001263801"
  }, 
  "runtime": {
    "docker": null
  }
}