{
  "task": "xml_file_upload", 
  "depends_on": [
    "completed@xml_upload_to_aws", 
    "completed@prepare_metadata_xml"
  ], 
  "tool": "upload", 
  "command": "upload.py", 
  "output": [
    {
      "_jt_": {
        "worker_id": "worker.1499715228.c40c55ff.host.76674056.10.10.0.19", 
        "workflow_version": "0.6.7", 
        "jt_version": "0.1.0rc9", 
        "task_state": "completed"
      }, 
      "runtime": {
        "task_start": 1499932625, 
        "task_stop": 1499932640
      }
    }
  ], 
  "input": {
    "file_name": "bundle.EGAR00001194575.xml", 
    "object_id": "bef8c743-8d11-5fd3-985f-c2b356c4907c", 
    "file_md5sum": "b7724c3b07f416d055d27566d6ff6199", 
    "file": "/home/ubuntu/jtracker/worker.1499715228.c40c55ff.host.76674056.10.10.0.19/job.EGAR00001194575.LINC-JP.CCC4T.EGAN00001196926/task.prepare_metadata_xml/bundle.EGAR00001194575.xml", 
    "file_size": 3499, 
    "bundle_id": "EGAR00001194575"
  }, 
  "runtime": {
    "docker": null
  }
}