{
  "task": "xml_file_upload", 
  "depends_on": [
    "completed@xml_upload_to_aws", 
    "completed@prepare_metadata_xml"
  ], 
  "tool": "upload", 
  "command": "upload.py", 
  "output": [
    {
      "_jt_": {
        "worker_id": "worker.1499805416.a2426c62.host.231181a3.10.10.1.7", 
        "workflow_version": "0.6.7", 
        "jt_version": "0.1.0rc9", 
        "task_state": "completed"
      }, 
      "runtime": {
        "task_start": 1499945097, 
        "task_stop": 1499945112
      }
    }
  ], 
  "input": {
    "file_name": "bundle.EGAR00001194611.xml", 
    "object_id": "79080565-e0a2-5dc8-b23f-017c669937a5", 
    "file_md5sum": "b9f94bf144c75e8c2dd120875c069b05", 
    "file": "/home/ubuntu/jtracker/worker.1499805416.a2426c62.host.231181a3.10.10.1.7/job.EGAR00001194611.LINC-JP.CCC4T.EGAN00001196926/task.prepare_metadata_xml/bundle.EGAR00001194611.xml", 
    "file_size": 3497, 
    "bundle_id": "EGAR00001194611"
  }, 
  "runtime": {
    "docker": null
  }
}