{
  "task": "xml_upload_to_aws", 
  "depends_on": [
    "completed@prepare_metadata_xml"
  ], 
  "tool": "upload_to_aws", 
  "command": "upload_to_aws.py", 
  "input": {
    "file_name": "bundle.EGAR00001114923.xml", 
    "object_id": "2d0d4c39-095b-511e-bc6b-0589a530d3c8", 
    "file_md5sum": "f5c0312124daeb5c0b54dd2085167cfd", 
    "file": "/home/ubuntu/jtracker/worker.1499715228.c40c55ff.host.76674056.10.10.0.19/job.EGAR00001114923.LINC-JP.HCC78T.EGAN00001086028/task.prepare_metadata_xml/bundle.EGAR00001114923.xml", 
    "file_size": 3663, 
    "bundle_id": "EGAR00001114923", 
    "project_code": "LINC-JP"
  }, 
  "runtime": {
    "docker": null
  }
}