{
  "task": "xml_file_upload", 
  "depends_on": [
    "completed@xml_upload_to_aws", 
    "completed@prepare_metadata_xml"
  ], 
  "tool": "upload", 
  "command": "upload.py", 
  "output": [
    {
      "_jt_": {
        "worker_id": "worker.1505228119.1208260d.host.4b92f40d.10.10.0.3", 
        "workflow_version": "0.6.11", 
        "jt_version": "0.1.0rc9", 
        "task_state": "completed"
      }, 
      "runtime": {
        "task_start": 1505496014, 
        "task_stop": 1505496036
      }
    }
  ], 
  "input": {
    "file_name": "bundle.EGAR00001351990.xml", 
    "object_id": "4e5f4c9a-90f7-546a-b9d6-2b51fb5f60fe", 
    "file_md5sum": "b540b3d66926ead734e4c2b3b00babeb", 
    "file": "/home/ubuntu/jtracker/worker.1505228119.1208260d.host.4b92f40d.10.10.0.3/job.EGAR00001351990.SKCA-BR.ML_35_T_01.EGAN00001295740/task.prepare_metadata_xml/bundle.EGAR00001351990.xml", 
    "file_size": 4297, 
    "bundle_id": "EGAR00001351990"
  }, 
  "runtime": {
    "docker": null
  }
}