{
  "task": "prepare_metadata_xml", 
  "depends_on": null, 
  "tool": "prepare_metadata_xml", 
  "command": "prepare_metadata_xml.py", 
  "output": [
    {
      "xml_file_md5sum": "bcb2bd1fb674a9a27506851f518e24d8", 
      "xml_file_name": "bundle.EGAR00001119634.xml", 
      "xml_file": "/home/ubuntu/jtracker/worker.1499440260.5b83a08c.host.231181a3.10.10.1.7/job.EGAR00001119634.LINC-JP.HCC134T.EGAN00001086070/task.prepare_metadata_xml/bundle.EGAR00001119634.xml", 
      "_jt_": {
        "worker_id": "worker.1499440260.5b83a08c.host.231181a3.10.10.1.7", 
        "workflow_version": "0.6.6", 
        "jt_version": "0.1.0rc9", 
        "task_state": "completed"
      }, 
      "xml_file_size": 3669, 
      "runtime": {
        "task_start": 1499455412, 
        "task_stop": 1499455412
      }
    }
  ], 
  "input": {
    "ega_metadata_repo": "https://raw.githubusercontent.com/icgc-dcc/ega-file-transfer/master/ega_xml/v20170522", 
    "ega_metadata_file_name": "bundle.EGAR00001119634.xml", 
    "ega_study_id": "EGAS00001000389", 
    "ega_dataset_id": "EGAD00001000446", 
    "ega_sample_id": "EGAN00001086070", 
    "ega_analysis_id": null, 
    "ega_experiment_id": "EGAX00001115910", 
    "bundle_id": "EGAR00001119634", 
    "project_code": "LINC-JP", 
    "ega_run_id": "EGAR00001119634"
  }, 
  "runtime": {
    "docker": null
  }
}