{
  "task": "xml_upload_to_aws", 
  "depends_on": [
    "completed@prepare_metadata_xml"
  ], 
  "tool": "upload_to_aws", 
  "command": "upload_to_aws.py", 
  "output": [
    {
      "_jt_": {
        "worker_id": "worker.1499458072.f5d200cb.host.76674056.10.10.0.19", 
        "workflow_version": "0.6.7", 
        "jt_version": "0.1.0rc9", 
        "task_state": "failed"
      }
    }
  ], 
  "input": {
    "file_name": "bundle.EGAR00001117759.xml", 
    "object_id": "a0206f6e-211a-5375-8b73-ae6cb8c2f7ec", 
    "file_md5sum": "028a9f5e80586df1fe69d128a50fe92e", 
    "file": "/home/ubuntu/jtracker/worker.1499458072.f5d200cb.host.76674056.10.10.0.19/job.EGAR00001117759.LINC-JP.HCC107T.EGAN00001086050/task.prepare_metadata_xml/bundle.EGAR00001117759.xml", 
    "file_size": 3671, 
    "bundle_id": "EGAR00001117759", 
    "project_code": "LINC-JP"
  }, 
  "runtime": {
    "docker": null
  }
}