{
  "task": "xml_upload_to_aws", 
  "depends_on": [
    "completed@prepare_metadata_xml"
  ], 
  "tool": "upload_to_aws", 
  "command": "upload_to_aws.py", 
  "input": {
    "file_name": "bundle.EGAR00001263334.xml", 
    "object_id": "ed1d6053-de79-518f-8937-4ea595f7ae1c", 
    "file_md5sum": "bac15e5b2a1f72f63d155e2e75a8e8ed", 
    "file": "/home/ubuntu/jtracker/worker.1499805416.a2426c62.host.231181a3.10.10.1.7/job.EGAR00001263334.BTCA-JP.BD214T.EGAN00001247007/task.prepare_metadata_xml/bundle.EGAR00001263334.xml", 
    "file_size": 3186, 
    "bundle_id": "EGAR00001263334", 
    "project_code": "BTCA-JP"
  }, 
  "runtime": {
    "docker": null
  }
}