{
  "task": "xml_file_upload", 
  "depends_on": [
    "completed@xml_upload_to_aws", 
    "completed@prepare_metadata_xml"
  ], 
  "tool": "upload", 
  "command": "upload.py", 
  "output": [
    {
      "_jt_": {
        "worker_id": "worker.1499784243.85d5d05e.host.032f1807.10.10.0.3", 
        "workflow_version": "0.6.7", 
        "jt_version": "0.1.0rc9", 
        "task_state": "completed"
      }, 
      "runtime": {
        "task_start": 1500117351, 
        "task_stop": 1500117367
      }
    }
  ], 
  "input": {
    "file_name": "bundle.EGAR00001199910.xml", 
    "object_id": "2c2506a9-d372-55e0-845c-f77b5046a783", 
    "file_md5sum": "54df44513b19e47addf57316ba50ac9a", 
    "file": "/home/ubuntu/jtracker/worker.1499784243.85d5d05e.host.032f1807.10.10.0.3/job.EGAR00001199910.LINC-JP.HCC80T.EGAN00001196879/task.prepare_metadata_xml/bundle.EGAR00001199910.xml", 
    "file_size": 3497, 
    "bundle_id": "EGAR00001199910"
  }, 
  "runtime": {
    "docker": null
  }
}