{
  "task": "xml_upload_to_aws", 
  "depends_on": [
    "completed@prepare_metadata_xml"
  ], 
  "tool": "upload_to_aws", 
  "command": "upload_to_aws.py", 
  "input": {
    "file_name": "bundle.EGAR00001264411.xml", 
    "object_id": "1dcc9c22-7315-5006-9d1e-ffc8008816e9", 
    "file_md5sum": "b6f5ddf6dc972aed34959e29737412d4", 
    "file": "/home/ubuntu/jtracker/worker.1499715228.c40c55ff.host.76674056.10.10.0.19/job.EGAR00001264411.BTCA-JP.BD236T.EGAN00001247029/task.prepare_metadata_xml/bundle.EGAR00001264411.xml", 
    "file_size": 3186, 
    "bundle_id": "EGAR00001264411", 
    "project_code": "BTCA-JP"
  }, 
  "runtime": {
    "docker": null
  }
}