{
  "task": "xml_upload_to_aws", 
  "depends_on": [
    "completed@prepare_metadata_xml"
  ], 
  "tool": "upload_to_aws", 
  "command": "upload_to_aws.py", 
  "input": {
    "file_name": "bundle.EGAR00001119435.xml", 
    "object_id": "3688dc1c-3f35-5930-b24a-e199264daf38", 
    "file_md5sum": "83c663e80bae7f16131f392e0f9e27be", 
    "file": "/home/ubuntu/jtracker/worker.1499364148.607fa559.host.76674056.10.10.0.19/job.EGAR00001119435.LINC-JP.HCC130T.EGAN00001086066/task.prepare_metadata_xml/bundle.EGAR00001119435.xml", 
    "file_size": 3667, 
    "bundle_id": "EGAR00001119435", 
    "project_code": "LINC-JP"
  }, 
  "runtime": {
    "docker": null
  }
}