{
  "task": "xml_upload_to_aws", 
  "depends_on": [
    "completed@prepare_metadata_xml"
  ], 
  "tool": "upload_to_aws", 
  "command": "upload_to_aws.py", 
  "output": [
    {
      "idx_file_size": 0, 
      "idx_file_md5sum": null, 
      "_jt_": {
        "worker_id": "worker.1502297050.f3b776c4.host.2b33d591.10.10.0.20", 
        "workflow_version": "0.6.7", 
        "jt_version": "0.1.0rc9", 
        "task_state": "completed"
      }, 
      "idx_file": null, 
      "allowed_upload": false, 
      "file_md5sum": "730e35728d1ab9b36ee9972562807275", 
      "file": "/home/ubuntu/jtracker/worker.1502297050.f3b776c4.host.2b33d591.10.10.0.20/job.EGAR00001263973.BTCA-JP.BD225T.EGAN00001247018/task.prepare_metadata_xml/bundle.EGAR00001263973.xml", 
      "file_size": 0, 
      "runtime": {
        "task_start": 1502954898, 
        "task_stop": 1502954898
      }
    }
  ], 
  "input": {
    "file_name": "bundle.EGAR00001263973.xml", 
    "object_id": "1d23d6b9-8625-5423-beda-1d0bce511422", 
    "file_md5sum": "730e35728d1ab9b36ee9972562807275", 
    "file": "/home/ubuntu/jtracker/worker.1502297050.f3b776c4.host.2b33d591.10.10.0.20/job.EGAR00001263973.BTCA-JP.BD225T.EGAN00001247018/task.prepare_metadata_xml/bundle.EGAR00001263973.xml", 
    "file_size": 3186, 
    "bundle_id": "EGAR00001263973", 
    "project_code": "BTCA-JP"
  }, 
  "runtime": {
    "docker": null
  }
}