{
  "task": "xml_file_upload", 
  "depends_on": [
    "completed@xml_upload_to_aws", 
    "completed@prepare_metadata_xml"
  ], 
  "tool": "upload", 
  "command": "upload.py", 
  "input": {
    "file_name": "bundle.EGAR00001114406.xml", 
    "object_id": "e8eceb57-9347-5ff5-b281-754c1c3c8d9e", 
    "file_md5sum": "84a551bbfc52d74017a0492301ddea4d", 
    "file": "/home/ubuntu/jtracker/worker.1499457168.ac01eac3.host.231181a3.10.10.1.7/job.EGAR00001114406.LINC-JP.HCC71T.EGAN00001086021/task.prepare_metadata_xml/bundle.EGAR00001114406.xml", 
    "file_size": 3665, 
    "bundle_id": "EGAR00001114406"
  }, 
  "runtime": {
    "docker": null
  }
}