{
  "task": "xml_file_upload", 
  "depends_on": [
    "completed@xml_upload_to_aws", 
    "completed@prepare_metadata_xml"
  ], 
  "tool": "upload", 
  "command": "upload.py", 
  "output": [
    {
      "_jt_": {
        "worker_id": "worker.1499458072.f5d200cb.host.76674056.10.10.0.19", 
        "workflow_version": "0.6.7", 
        "jt_version": "0.1.0rc9", 
        "task_state": "completed"
      }, 
      "runtime": {
        "task_start": 1499472029, 
        "task_stop": 1499472043
      }
    }
  ], 
  "input": {
    "file_name": "bundle.EGAR00001114606.xml", 
    "object_id": "a1ed06fa-431e-5c51-8b07-83948b8c2a74", 
    "file_md5sum": "08c26c69f8b2cb194ce461cca7ed210d", 
    "file": "/home/ubuntu/jtracker/worker.1499458072.f5d200cb.host.76674056.10.10.0.19/job.EGAR00001114606.LINC-JP.HCC74T.EGAN00001086024/task.prepare_metadata_xml/bundle.EGAR00001114606.xml", 
    "file_size": 3665, 
    "bundle_id": "EGAR00001114606"
  }, 
  "runtime": {
    "docker": null
  }
}