{
  "task": "xml_upload_to_aws", 
  "depends_on": [
    "completed@prepare_metadata_xml"
  ], 
  "tool": "upload_to_aws", 
  "command": "upload_to_aws.py", 
  "input": {
    "file_name": "bundle.EGAR00001262947.xml", 
    "object_id": "2220c796-521c-5f52-9761-c2764ec6c0f8", 
    "file_md5sum": "10c63b164ff67b1f6a7878cd7a2a9e9a", 
    "file": "/home/ubuntu/jtracker/worker.1502297042.33adc75f.host.2b33d591.10.10.0.20/job.EGAR00001262947.BTCA-JP.BD205T.EGAN00001246998/task.prepare_metadata_xml/bundle.EGAR00001262947.xml", 
    "file_size": 3184, 
    "bundle_id": "EGAR00001262947", 
    "project_code": "BTCA-JP"
  }, 
  "runtime": {
    "docker": null
  }
}