{
  "task": "xml_upload_to_aws", 
  "depends_on": [
    "completed@prepare_metadata_xml"
  ], 
  "tool": "upload_to_aws", 
  "command": "upload_to_aws.py", 
  "output": [
    {
      "idx_file_size": 0, 
      "idx_file_md5sum": null, 
      "_jt_": {
        "worker_id": "worker.1499784243.85d5d05e.host.032f1807.10.10.0.3", 
        "workflow_version": "0.6.7", 
        "jt_version": "0.1.0rc9", 
        "task_state": "completed"
      }, 
      "idx_file": null, 
      "allowed_upload": true, 
      "file_md5sum": "de81629ae8d3488816867a92259341a8", 
      "file": "/home/ubuntu/jtracker/worker.1499784243.85d5d05e.host.032f1807.10.10.0.3/job.EGAR00001115454.LINC-JP.HCC86T.EGAN00001086033/task.prepare_metadata_xml/bundle.EGAR00001115454.xml", 
      "file_size": 3665, 
      "runtime": {
        "task_start": 1500225707, 
        "task_stop": 1500225713
      }
    }
  ], 
  "input": {
    "file_name": "bundle.EGAR00001115454.xml", 
    "object_id": "66b9540e-083a-58a6-87d9-e7bcc540b3ac", 
    "file_md5sum": "de81629ae8d3488816867a92259341a8", 
    "file": "/home/ubuntu/jtracker/worker.1499784243.85d5d05e.host.032f1807.10.10.0.3/job.EGAR00001115454.LINC-JP.HCC86T.EGAN00001086033/task.prepare_metadata_xml/bundle.EGAR00001115454.xml", 
    "file_size": 3665, 
    "bundle_id": "EGAR00001115454", 
    "project_code": "LINC-JP"
  }, 
  "runtime": {
    "docker": null
  }
}