{
  "task": "xml_file_upload", 
  "depends_on": [
    "completed@xml_upload_to_aws", 
    "completed@prepare_metadata_xml"
  ], 
  "tool": "upload", 
  "command": "upload.py", 
  "input": {
    "file_name": "bundle.EGAR00001199708.xml", 
    "object_id": "e2334320-64e2-5408-80de-22fda6d726a6", 
    "file_md5sum": "9e1925fc53e48f8fbccc945a49482aed", 
    "file": "/home/ubuntu/jtracker/worker.1499715228.c40c55ff.host.76674056.10.10.0.19/job.EGAR00001199708.LINC-JP.HCC79T.EGAN00001196878/task.prepare_metadata_xml/bundle.EGAR00001199708.xml", 
    "file_size": 3497, 
    "bundle_id": "EGAR00001199708"
  }, 
  "runtime": {
    "docker": null
  }
}