{
  "task": "xml_file_upload", 
  "depends_on": [
    "completed@xml_upload_to_aws", 
    "completed@prepare_metadata_xml"
  ], 
  "tool": "upload", 
  "command": "upload.py", 
  "input": {
    "file_name": "bundle.EGAR00001263870.xml", 
    "object_id": "75d3cfe5-ec42-572b-83cb-1abd60f1fd26", 
    "file_md5sum": "f3245f349cfbaedcd9f28935e94d270a", 
    "file": "/home/ubuntu/jtracker/worker.1499715228.c40c55ff.host.76674056.10.10.0.19/job.EGAR00001263870.BTCA-JP.BD223T.EGAN00001247016/task.prepare_metadata_xml/bundle.EGAR00001263870.xml", 
    "file_size": 3186, 
    "bundle_id": "EGAR00001263870"
  }, 
  "runtime": {
    "docker": null
  }
}