{
  "task": "xml_file_upload", 
  "depends_on": [
    "completed@xml_upload_to_aws", 
    "completed@prepare_metadata_xml"
  ], 
  "tool": "upload", 
  "command": "upload.py", 
  "input": {
    "file_name": "bundle.EGAR00001114589.xml", 
    "object_id": "44ab3246-e8f1-524d-9718-7c0a5f4814b5", 
    "file_md5sum": "28caa15bfa26ec0099285667f18cb110", 
    "file": "/home/ubuntu/jtracker/worker.1499460317.ae7ebd11.host.032f1807.10.10.0.3/job.EGAR00001114589.LINC-JP.HCC74T.EGAN00001086024/task.prepare_metadata_xml/bundle.EGAR00001114589.xml", 
    "file_size": 3665, 
    "bundle_id": "EGAR00001114589"
  }, 
  "runtime": {
    "docker": null
  }
}